[
  {
    "name": "Calvin Chueh",
    "submission": "on time"
  },
  {
    "name": "Becky DeNardis",
    "submission": "on time"
  },
  {
    "name": "Sam Ginsburg",
    "submission": "on time"
  },
  {
    "name": "Nicholas Gordon",
    "submission": "on time"
  },
  {
    "name": "Jesse Hu",
    "submission": "on time"
  },
  {
    "name": "Ouwen Huang",
    "submission": "on time"
  },
  {
    "name": "Yu Zhou Lee",
    "submission": "on time"
  },
  {
    "name": "Peggy Li",
    "submission": "on time"
  },
  {
    "name": "Tim Luu",
    "submission": "on time"
  },
  {
    "name": "Ian McKiernan",
    "submission": "late"
  },
  {
    "name": "Josh Miller",
    "submission": "on time"
  },
  {
    "name": "Zanele Munyikwa",
    "submission": "on time"
  },
  {
    "name": "Sarah Rowan",
    "submission": "on time"
  },
  {
    "name": "Bradley Sykes",
    "submission": "on time"
  }
]